{
	"sn": "facebook",
	"custom": {},
	"lastEventDate": "09.03.2024 22:37 TEST",
	"status": 2,
	"id": "61553321702863",
	"name": "",
	"profileName": "Kamilla Butenko",
	"amountFriends": "",
	"screenname": "Kamilla Butenko",
	"birthdate": "1998 February 7",
	"country": "",
	"isAvatarExists": false,
	"cookie": [
		{
			"domain": ".facebook.com",
			"expirationDate": 1741203558.050712,
			"hostOnly": false,
			"httpOnly": false,
			"name": "c_user",
			"path": "/",
			"sameSite": "no_restriction",
			"secure": true,
			"session": false,
			"storeId": "0",
			"value": "61553321702863"
		},
		{
			"domain": ".facebook.com",
			"expirationDate": 1741115425,
			"hostOnly": false,
			"httpOnly": false,
			"name": "usida",
			"path": "/",
			"sameSite": "lax",
			"secure": true,
			"session": false,
			"storeId": "0",
			"value": "eyJ2ZXIiOjEsImlkIjoiQXM5cTdxM2Y3dmllNSIsInRpbWUiOjE3MDkzOTI1Mzl9"
		},
		{
			"domain": ".facebook.com",
			"expirationDate": 1741115425,
			"hostOnly": false,
			"httpOnly": false,
			"name": "sb",
			"path": "/",
			"sameSite": "lax",
			"secure": true,
			"session": false,
			"storeId": "0",
			"value": "NZKLZfkhShycMAxgi36-WEOW"
		},
		{
			"domain": ".facebook.com",
			"expirationDate": 1741115425,
			"hostOnly": false,
			"httpOnly": false,
			"name": "ps_n",
			"path": "/",
			"sameSite": "lax",
			"secure": true,
			"session": false,
			"storeId": "0",
			"value": "0"
		},
		{
			"domain": ".facebook.com",
			"expirationDate": 1741115425,
			"hostOnly": false,
			"httpOnly": false,
			"name": "ps_l",
			"path": "/",
			"sameSite": "lax",
			"secure": true,
			"session": false,
			"storeId": "0",
			"value": "0"
		},
		{
			"domain": ".facebook.com",
			"expirationDate": 1741115425,
			"hostOnly": false,
			"httpOnly": false,
			"name": "m_page_voice",
			"path": "/",
			"sameSite": "lax",
			"secure": true,
			"session": false,
			"storeId": "0",
			"value": "61553321702863"
		},
		{
			"domain": ".facebook.com",
			"expirationDate": 1741115425,
			"hostOnly": false,
			"httpOnly": false,
			"name": "datr",
			"path": "/",
			"sameSite": "lax",
			"secure": true,
			"session": false,
			"storeId": "0",
			"value": "NJKLZd39UQpTgp-p-nqJ8kVY"
		},
		{
			"domain": ".facebook.com",
			"expirationDate": 1741115425,
			"hostOnly": false,
			"httpOnly": false,
			"name": "cppo",
			"path": "/",
			"sameSite": "lax",
			"secure": true,
			"session": false,
			"storeId": "0",
			"value": "1"
		},
		{
			"domain": ".facebook.com",
			"expirationDate": 1741203558.050801,
			"hostOnly": false,
			"httpOnly": true,
			"name": "xs",
			"path": "/",
			"sameSite": "no_restriction",
			"secure": true,
			"session": false,
			"storeId": "0",
			"value": "8%3ANiHR6ICjsd7y5Q%3A2%3A1703645787%3A-1%3A-1%3A%3AAcXlMZgEJ4AtwvCCFddKQr9sZscnd_Vh1pdI6SIhUQ"
		},
		{
			"domain": ".facebook.com",
			"expirationDate": 1710272364,
			"hostOnly": false,
			"httpOnly": false,
			"name": "dpr",
			"path": "/",
			"sameSite": "no_restriction",
			"secure": true,
			"session": false,
			"storeId": "0",
			"value": "2"
		},
		{
			"domain": ".facebook.com",
			"expirationDate": 1710272437,
			"hostOnly": false,
			"httpOnly": false,
			"name": "wd",
			"path": "/",
			"sameSite": "lax",
			"secure": true,
			"session": false,
			"storeId": "0",
			"value": "1218x567"
		},
		{
			"domain": ".facebook.com",
			"expirationDate": 1717443577.64621,
			"hostOnly": false,
			"httpOnly": true,
			"name": "fr",
			"path": "/",
			"sameSite": "no_restriction",
			"secure": true,
			"session": false,
			"storeId": "0",
			"value": "1cxNwMBG09xSzbinp.AWWAcxPjcZ4tqBkNeNT518bzZ8c.Bl53Tl..AAA.0.0.Bl53T5.AWV3pcTNZTQ"
		},
		{
			"domain": ".facebook.com",
			"hostOnly": false,
			"httpOnly": false,
			"name": "presence",
			"path": "/",
			"sameSite": "unspecified",
			"secure": true,
			"session": true,
			"storeId": "0",
			"value": "C%7B%22t3%22%3A%5B%5D%2C%22utc3%22%3A1709667638524%2C%22v%22%3A1%7D"
		}
	]
}